LICENSE
MANIFEST.in
README.md
pyproject.toml
setup.py
design3d/__init__.py
design3d/cad_simplification.py
design3d/cloud.py
design3d/core.py
design3d/core_compiled.pxd
design3d/core_compiled.pyx
design3d/curves.py
design3d/discrete_representation.py
design3d/discrete_representation_compiled.cpp
design3d/discrete_representation_compiled.py
design3d/display.py
design3d/edges.py
design3d/faces.py
design3d/geometry.py
design3d/gmsh_vm.py
design3d/grid.py
design3d/mesh.py
design3d/primitives.py
design3d/primitives2d.py
design3d/primitives3d.py
design3d/shells.py
design3d/step.py
design3d/stl.py
design3d/surfaces.py
design3d/templates.py
design3d/wires.py
design3d.egg-info/PKG-INFO
design3d.egg-info/SOURCES.txt
design3d.egg-info/dependency_links.txt
design3d.egg-info/requires.txt
design3d.egg-info/top_level.txt
design3d/assets/js/babylon.js
design3d/assets/js/babylonjs.loaders.min.js
design3d/assets/js/earcut.min.js
design3d/assets/js/pep.js
design3d/assets/logos/volmdlr.jpg
design3d/nurbs/__init__.py
design3d/nurbs/core.cpp
design3d/nurbs/core.pyx
design3d/nurbs/fitting.cpp
design3d/nurbs/fitting.py
design3d/nurbs/helpers.cpp
design3d/nurbs/helpers.pxd
design3d/nurbs/helpers.pyx
design3d/nurbs/operations.c
design3d/nurbs/operations.py
design3d/utils/__init__.py
design3d/utils/common_operations.py
design3d/utils/intersections.py
design3d/utils/parametric.py
design3d/utils/step_reader.py
design3d/utils/step_writer.py
tests/test_cloud.py
tests/test_core.py
tests/test_geometry.py