Metadata-Version: 2.2
Name: design3d
Version: 0.3.1.dev19
Summary:  A volume modeler computation-oriented. Include rendering bindings.
Home-page: https://github.com/masfaraud/design3d
Author: Steven Masfaraud
Author-email: design3d@masfaraud.fr
License: Creative Commons Attribution-Share Alike license
Keywords: volume,modeler,CAD
Classifier: Topic :: Scientific/Engineering
Classifier: Topic :: Multimedia :: Graphics :: 3D Modeling
Classifier: Development Status :: 5 - Production/Stable
Requires-Python: >=3.9
License-File: LICENSE
Requires-Dist: packaging
Requires-Dist: Cython>=3.0.0
Requires-Dist: numpy
Requires-Dist: matplotlib
Requires-Dist: scipy
Requires-Dist: geomdl
Requires-Dist: networkx
Requires-Dist: triangle
Requires-Dist: kaitaistruct
Requires-Dist: binaryornot
Requires-Dist: sympy
Requires-Dist: trimesh
Requires-Dist: rtree
Requires-Dist: gmsh
Requires-Dist: pyfqmr
Requires-Dist: CGAL
Requires-Dist: scikit-learn
Provides-Extra: test
Requires-Dist: coverage; extra == "test"
Provides-Extra: doc
Requires-Dist: sphinx; extra == "doc"
Requires-Dist: nbsphinx; extra == "doc"
Requires-Dist: pydata_sphinx_theme; extra == "doc"
Requires-Dist: nbformat; extra == "doc"
Requires-Dist: nbconvert; extra == "doc"
Requires-Dist: sphinx_copybutton; extra == "doc"
Requires-Dist: sphinx_design; extra == "doc"
Dynamic: author
Dynamic: author-email
Dynamic: classifier
Dynamic: description
Dynamic: description-content-type
Dynamic: home-page
Dynamic: keywords
Dynamic: license
Dynamic: provides-extra
Dynamic: requires-dist
Dynamic: requires-python
Dynamic: summary
